papflix/__init__.py
papflix/main.py
papflix/model/__init__.py
papflix/model/cast.py
papflix/model/custom_models.py
papflix/model/movie.py
papflix_kpaparid-0.0.5.dist-info/LICENSE
papflix_kpaparid-0.0.5.dist-info/METADATA
papflix_kpaparid-0.0.5.dist-info/WHEEL
papflix_kpaparid-0.0.5.dist-info/top_level.txt
papflix_kpaparid-0.0.5.dist-info/RECORD
